seedweed/__init__.py
seedweed/conformance.py
seedweed/reference.py
seedweed/test-vectors.csv
seedweed/vectors.py
seedweed-1.0rc7.dist-info/entry_points.txt
seedweed-1.0rc7.dist-info/LICENSE-APACHE
seedweed-1.0rc7.dist-info/LICENSE-MIT
seedweed-1.0rc7.dist-info/WHEEL
seedweed-1.0rc7.dist-info/METADATA
seedweed-1.0rc7.dist-info/RECORD
