Metadata-Version: 2.1
Name: seedweed
Version: 1.0rc7
Summary: Seeded WebAuthn Credentials: reference implementation
Home-page: https://github.com/solokeys/seedweed
License: UNKNOWN
Author: Nicolas Stalder
Author-email: nicolas@solokeys.com
Requires-Python: ~=3.6
Classifier: License :: OSI Approved :: Apache Software License
Classifier: License :: OSI Approved :: MIT License
Classifier: Intended Audience :: Developers
Classifier: Programming Language :: Python :: 3 :: Only
Classifier: Programming Language :: Python :: 3.6
Classifier: Programming Language :: Python :: 3.7
Classifier: Programming Language :: Python :: 3.8
Classifier: Programming Language :: Python :: 3.9
Requires-Dist: ecdsa >= 0.16.0
